vcs/main.py
vcs/commands/add.py
vcs/commands/checkout.py
vcs/commands/cleanup.py
vcs/commands/commit.py
vcs/commands/init.py
vcs/commands/log.py
vcs/commands/show.py
py_vcs_lite-0.1.3.dist-info/METADATA
py_vcs_lite-0.1.3.dist-info/WHEEL
py_vcs_lite-0.1.3.dist-info/entry_points.txt
py_vcs_lite-0.1.3.dist-info/top_level.txt
py_vcs_lite-0.1.3.dist-info/RECORD
