Metadata-Version: 2.4
Name: py-vcs-lite
Version: 0.1.3
Summary: A lightweight Git-like version control system
Author: Arjun
License-Expression: MIT
Classifier: Programming Language :: Python :: 3
Classifier: Operating System :: OS Independent
Requires-Python: >=3.7
